{
  "package": {
    "uri": "http://www.compute.dtu.dk/sse/models/petri-net",
    "objects": [
      {
        "name": "pn1",
        "type": {
          "$ref": "http://www.compute.dtu.dk/sse/models/petri-net#/classes/0"
        },
        "attributes": [],
        "links": [
          {
            "name": "object",
            "target": {
              "$ref": "#/objects/1"
            }
          }
        ]
      },
      {
        "name": "a1",
        "type": "Arc",
        "attributes": [],
        "links": [
          {
            "name": "target",
            "target": {
              "$ref": "#/objects/2"
            }
          },
          {
            "name": "source",
            "target": {
              "$ref": "#/objects/3"
            }
          }
        ]
      },
      {
        "name": "pl1",
        "type": "Place",
        "attributes": [],
        "links": [
          {
            "name": "petriNet",
            "target": {
              "$ref": "#/objects/0"
            }
          },
          {
            "name": "token",
            "target": {
              "$ref": "#/objects/4"
            }
          }
        ]
      },
      {
        "name": "tr1",
        "type": "Transition",
        "attributes": [],
        "links": [
          {
            "name": "petriNet",
            "target": {
              "$ref": "#/objects/0"
            }
          }
        ]
      },
      {
        "name": "t1",
        "type": "Token",
        "attributes": [],
        "links": [
          {
            "name": "place",
            "target": {
              "$ref": "#/objects/2"
            }
          }
        ]
      }
    ]
  }
}
